polyswarm_engine/__init__.py
polyswarm_engine/backend.py
polyswarm_engine/bidutils.py
polyswarm_engine/bounty.py
polyswarm_engine/celeryconfig.py
polyswarm_engine/cli.py
polyswarm_engine/command.py
polyswarm_engine/constants.py
polyswarm_engine/engine.py
polyswarm_engine/exceptions.py
polyswarm_engine/log_config.py
polyswarm_engine/py.typed
polyswarm_engine/settings.py
polyswarm_engine/typing.py
polyswarm_engine/utils.py
polyswarm_engine/wine.py
polyswarm_engine/wsgi.py
polyswarm_engine-3.2.2.dist-info/METADATA
polyswarm_engine-3.2.2.dist-info/WHEEL
polyswarm_engine-3.2.2.dist-info/top_level.txt
polyswarm_engine-3.2.2.dist-info/RECORD
