Metadata-Version: 2.4
Name: polyswarm_engine
Version: 3.2.2
Summary: Polyswarm engine libarary
Author-email: Polyswarm Developers <developers@polyswarm.io>
Project-URL: Homepage, https://github.com/polyswarm/polyswarm_engine
Requires-Python: <4,>=3.8
Requires-Dist: celery
Requires-Dist: click
Requires-Dist: click-log
Requires-Dist: python-json-logger
Requires-Dist: requests
Provides-Extra: tests
Requires-Dist: pathlib3x; python_version < "3.10" and extra == "tests"
Requires-Dist: flake8; extra == "tests"
Requires-Dist: isort; extra == "tests"
Requires-Dist: mypy; extra == "tests"
Requires-Dist: pytest>=7.0; extra == "tests"
Requires-Dist: types-requests; extra == "tests"
Requires-Dist: yapf; extra == "tests"
Provides-Extra: web
Requires-Dist: flask; extra == "web"
Requires-Dist: gunicorn; extra == "web"
